{
  "id": "swsh9-144",
  "name": "Magma Basin",
  "supertype": "Trainer",
  "subtypes": [
    "Stadium"
  ],
  "rules": [
    "Once during each player's turn, that player may attach a Fire Energy card from their discard pile to 1 of their Benched Fire Pokémon. If a player attached Energy to a Pokémon in this way, put 2 damage counters on that Pokémon."
  ],
  "set": {
    "id": "swsh9",
    "name": "Brilliant Stars",
    "series": "Sword & Shield",
    "printedTotal": 172,
    "total": 186,
    "legalities": {
      "unlimited": "Legal",
      "standard": "Legal",
      "expanded": "Legal"
    },
    "ptcgoCode": "BRS",
    "releaseDate": "2022/02/25",
    "updatedAt": "2022/02/23 09:45:00",
    "images": {
      "symbol": "https://images.pokemontcg.io/swsh9/symbol.png",
      "logo": "https://images.pokemontcg.io/swsh9/logo.png"
    }
  },
  "number": "144",
  "artist": "ORBITALLINK Inc.",
  "rarity": "Uncommon",
  "legalities": {
    "unlimited": "Legal",
    "standard": "Legal",
    "expanded": "Legal"
  },
  "regulationMark": "F",
  "images": {
    "small": "https://images.pokemontcg.io/swsh9/144.png",
    "large": "https://images.pokemontcg.io/swsh9/144_hires.png"
  }
}